viemind_notion_orm/__init__.py
viemind_notion_orm/client.py
viemind_notion_orm/exceptions.py
viemind_notion_orm/filters.py
viemind_notion_orm/models.py
viemind_notion_orm/README.md
viemind_notion_orm/schema_types.py
viemind_notion_orm/utils.py
viemind_notion_orm-0.1.1.dist-info/METADATA
viemind_notion_orm-0.1.1.dist-info/WHEEL
viemind_notion_orm-0.1.1.dist-info/RECORD
