Metadata-Version: 2.3
Name: viemind_notion_orm
Version: 0.1.1
Summary: Viebo Notion ORM
Author: thanhduy
Author-email: thanhduy@viemind.ai
Requires-Python: >=3.10,<4.0.0
Classifier: Programming Language :: Python :: 3
Classifier: Programming Language :: Python :: 3.10
Classifier: Programming Language :: Python :: 3.11
Classifier: Programming Language :: Python :: 3.12
Classifier: Programming Language :: Python :: 3.13
Requires-Dist: notion-client (>=2.4.0,<3.0.0)
